{
	"configurations" : 
	[
		{
			"directories" : 
			[
				{
					"build" : ".",
					"childIndexes" : 
					[
						1
					],
					"jsonFile" : "directory-.-Debug-d0094a50bb2071803777.json",
					"minimumCMakeVersion" : 
					{
						"string" : "3.25.0"
					},
					"projectIndex" : 0,
					"source" : "."
				},
				{
					"build" : "app",
					"jsonFile" : "directory-app-Debug-7ab44524cbd5ada90c6a.json",
					"minimumCMakeVersion" : 
					{
						"string" : "3.25.0"
					},
					"parentIndex" : 0,
					"projectIndex" : 0,
					"source" : "app",
					"targetIndexes" : 
					[
						0,
						1,
						2,
						3
					]
				}
			],
			"name" : "Debug",
			"projects" : 
			[
				{
					"directoryIndexes" : 
					[
						0,
						1
					],
					"name" : "Ctemplate",
					"targetIndexes" : 
					[
						0,
						1,
						2,
						3
					]
				}
			],
			"targets" : 
			[
				{
					"directoryIndex" : 1,
					"id" : "example::@5f5a17c01335469806cb",
					"jsonFile" : "target-example-Debug-cb3f749484a2fc4b3d4c.json",
					"name" : "example",
					"projectIndex" : 0
				},
				{
					"directoryIndex" : 1,
					"id" : "inv_mat::@5f5a17c01335469806cb",
					"jsonFile" : "target-inv_mat-Debug-c866efd7d2318f37243b.json",
					"name" : "inv_mat",
					"projectIndex" : 0
				},
				{
					"directoryIndex" : 1,
					"id" : "newc::@5f5a17c01335469806cb",
					"jsonFile" : "target-newc-Debug-8308880057c383f529ab.json",
					"name" : "newc",
					"projectIndex" : 0
				},
				{
					"directoryIndex" : 1,
					"id" : "newcpp::@5f5a17c01335469806cb",
					"jsonFile" : "target-newcpp-Debug-3927c9ed13e875ff821e.json",
					"name" : "newcpp",
					"projectIndex" : 0
				}
			]
		}
	],
	"kind" : "codemodel",
	"paths" : 
	{
		"build" : "D:/gitrepos/c_compile_test_cmake/build",
		"source" : "D:/gitrepos/c_compile_test_cmake"
	},
	"version" : 
	{
		"major" : 2,
		"minor" : 4
	}
}
